resources/conf.toml
resources/icon-help.png
resources/icon-label.png
resources/icon-open.png
resources/icon-save.png
resources/loading.gif
resources/qt_resources.qrc
resources/similarity.t7
sp_seg_tool/__init__.py
sp_seg_tool/__main__.py
sp_seg_tool/_version.py
sp_seg_tool/config.py
sp_seg_tool/main.py
sp_seg_tool/resources.py
sp_seg_tool/task.py
sp_seg_tool/backend/__init__.py
sp_seg_tool/backend/converters.py
sp_seg_tool/backend/labels.py
sp_seg_tool/backend/openers.py
sp_seg_tool/backend/state.py
sp_seg_tool/backend/utils.py
sp_seg_tool/gui/__init__.py
sp_seg_tool/gui/scene.py
sp_seg_tool/gui/toolbar.py
sp_seg_tool/gui/utils.py
sp_seg_tool/io/__init__.py
sp_seg_tool/io/utils.py
spseg_tool-2023.5a0.dist-info/LICENSE
spseg_tool-2023.5a0.dist-info/METADATA
spseg_tool-2023.5a0.dist-info/WHEEL
spseg_tool-2023.5a0.dist-info/entry_points.txt
spseg_tool-2023.5a0.dist-info/top_level.txt
spseg_tool-2023.5a0.dist-info/RECORD
