Metadata-Version: 2.1
Name: spseg-tool
Version: 2023.5a0
Summary: SP-SEG: Proof of concept tool for manual segmentation by spheripixel projection
Author-email: "Jakub Walczak, Adam Osuch, Adam Wojciechowski" <jakub.walczak@p.lodz.pl>
License: MIT License
Keywords: point cloud,segmentation
Classifier: Development Status :: 3 - Alpha
Classifier: Programming Language :: Python
Classifier: Environment :: Win32 (MS Windows)
Classifier: Operating System :: Microsoft :: Windows :: Windows 10
Classifier: Topic :: Multimedia :: Graphics :: Editors
Classifier: Topic :: Scientific/Engineering
Classifier: Topic :: Scientific/Engineering :: Image Processing
Classifier: Topic :: Scientific/Engineering :: Visualization
Requires-Python: >=3.10
License-File: LICENSE
Requires-Dist: PyQt5
Requires-Dist: numpy
Requires-Dist: pillow
Requires-Dist: pydantic
Requires-Dist: scikit-learn
Requires-Dist: scipy
Requires-Dist: colormath
Requires-Dist: tqdm
Requires-Dist: toml
